nsfw_screen_detect/__init__.py
nsfw_screen_detect/camera.py
nsfw_screen_detect/checker.py
nsfw_screen_detect/detector.py
nsfw_screen_detect/parser.py
nsfw_screen_detect/tests.py
nsfw_screen_detect/windows.py
nsfw_screen_detect/bin/lite_classifier.h5
nsfw_screen_detect-0.2.1.dist-info/LICENSE
nsfw_screen_detect-0.2.1.dist-info/METADATA
nsfw_screen_detect-0.2.1.dist-info/WHEEL
nsfw_screen_detect-0.2.1.dist-info/top_level.txt
nsfw_screen_detect-0.2.1.dist-info/RECORD
