Metadata-Version: 2.1
Name: nsfw-screen-detect
Version: 0.2.1
Summary: A small python package for detecting nsfw on a Windows display.
Home-page: https://github.com/dickermoshe/nsfw_detect_screenshot
Author: Moshe Dicker
Author-email: dickermoshe@gmail.com
License: GNU General Public License v3
Keywords: nsfw_screen_detect
Classifier: Development Status :: 2 - Pre-Alpha
Classifier: Intended Audience :: Developers
Classifier: License :: OSI Approved :: GNU General Public License v3 (GPLv3)
Classifier: Natural Language :: English
Classifier: Programming Language :: Python :: 3.10
Requires-Python: >=3.10
License-File: LICENSE
Requires-Dist: wheel
Requires-Dist: tensorflow
Requires-Dist: numpy
Requires-Dist: opencv-python
Requires-Dist: Pillow
Requires-Dist: mss
Requires-Dist: pywinauto
